just_agents/router/__init.__.py
just_agents/router/manager_agent.py
just_agents/router/secretary_agent.py
just_agents_router-0.8.7.dist-info/METADATA
just_agents_router-0.8.7.dist-info/WHEEL
just_agents_router-0.8.7.dist-info/RECORD
