Metadata-Version: 2.4
Name: just-agents-router
Version: 0.8.7
Summary: Just Agents - Router Components
License: MIT
Author: Newton Winter
Author-email: isoutthere@gmail.com
Maintainer: Newton Winter
Maintainer-email: isoutthere@gmail.com
Requires-Python: >=3.10,<3.15
Classifier: License :: OSI Approved :: MIT License
Classifier: Programming Language :: Python :: 3
Classifier: Programming Language :: Python :: 3.10
Classifier: Programming Language :: Python :: 3.11
Classifier: Programming Language :: Python :: 3.12
Classifier: Programming Language :: Python :: 3.13
Classifier: Programming Language :: Python :: 3.14
Requires-Dist: just-agents-core
